mbpprice/__init__.py
mbpprice/__main__.py
mbpprice/search.py
mbpprice-0.0.3.dist-info/LICENSE
mbpprice-0.0.3.dist-info/METADATA
mbpprice-0.0.3.dist-info/WHEEL
mbpprice-0.0.3.dist-info/top_level.txt
mbpprice-0.0.3.dist-info/RECORD
