Metadata-Version: 2.1
Name: mbpprice
Version: 0.0.3
Summary: second hand macbook pro price in Taiwan.
Home-page: https://github.com/allanbian1017/mbpprice
Author: Allan Bian
License: MIT
Platform: UNKNOWN
Requires-Python: >=3.5
Requires-Dist: pyquery
Requires-Dist: requests
